dmc/__init__.py
dmc/lrpc2.py
test.centrify.dmc-0.5.dist-info/LICENSE.txt
test.centrify.dmc-0.5.dist-info/METADATA
test.centrify.dmc-0.5.dist-info/WHEEL
test.centrify.dmc-0.5.dist-info/top_level.txt
test.centrify.dmc-0.5.dist-info/RECORD
