Metadata-Version: 2.1
Name: test.centrify.dmc
Version: 0.5
Summary: Library to retrieve an access token to Centrify PAS from an enrolled machine
Home-page: https://github.com/centrify/dmc-python
Author: Harvey Kwok
Author-email: harvey.kwok@centrify.com
License: apache-2.0
Download-URL: https://github.com/centrify/dmc-python/archive/v0.3-alpha.tar.gz
Keywords: Centrify,DMC,Windows,Linux,PAS
Platform: UNKNOWN
Classifier: Development Status :: 3 - Alpha
Classifier: Intended Audience :: Developers
Classifier: Topic :: Software Development :: Build Tools
Classifier: License :: OSI Approved :: Apache Software License
Classifier: Programming Language :: Python :: 3
Classifier: Programming Language :: Python :: 3.4
Classifier: Programming Language :: Python :: 3.5
Classifier: Programming Language :: Python :: 3.6
Classifier: Programming Language :: Python :: 3.7
Classifier: Operating System :: Microsoft :: Windows
Classifier: Operating System :: POSIX :: Linux
License-File: LICENSE.txt
